[
  {
    "id": "44a93007-a844-4165-8635-4385a88feb87",
    "name": "广州超品汇",
    "code": "SUP001",
    "type": "聚水潭",
    "channel": "聚水潭",
    "jd_channel_id": "",
    "express_restrictions": "[]",
    "contact": "",
    "phone": "",
    "address": "",
    "status": "active",
    "file": "assets/供应商发单/聚水潭-广州超品汇.xlsx"
  },
  {
    "id": "5e561dc9-834a-48ab-bf5e-b4b23ab921f0",
    "name": "广州首映礼",
    "code": "SUP002",
    "type": "聚水潭",
    "channel": "聚水潭",
    "jd_channel_id": "",
    "express_restrictions": "[]",
    "contact": "",
    "phone": "",
    "address": "",
    "status": "active",
    "file": "assets/供应商发单/聚水潭-广州首映礼.xlsx"
  },
  {
    "id": "3940838b-ae90-425d-a237-bd4601dcaa61",
    "name": "邵武万家美",
    "code": "SUP003",
    "type": "聚水潭",
    "channel": "聚水潭",
    "jd_channel_id": "",
    "express_restrictions": "[]",
    "contact": "",
    "phone": "",
    "address": "",
    "status": "active",
    "file": "assets/供应商发单/聚水潭-邵武万家美.xlsx"
  },
  {
    "id": "d464e221-3107-425d-b7ba-c4718a5d7ace",
    "name": "常州梁业",
    "code": "SUP004",
    "type": "其他",
    "channel": "其他",
    "jd_channel_id": "",
    "express_restrictions": "[]",
    "contact": "",
    "phone": "",
    "address": "",
    "status": "active",
    "file": "assets/供应商发单/常州梁业.xls"
  },
  {
    "id": "aa6bff71-11e9-4620-8de3-48d35e986680",
    "name": "北京金鼎越胜",
    "code": "SUP005",
    "type": "三方",
    "channel": "其他",
    "jd_channel_id": "",
    "express_restrictions": "[]",
    "contact": "",
    "phone": "",
    "address": "",
    "status": "active",
    "file": "历史发货成本资料"
  },
  {
    "id": "6c20a4a9-47e8-47f7-aa57-b5d4a12daab4",
    "name": "苏州合则盛",
    "code": "SUP006",
    "type": "三方",
    "channel": "其他",
    "jd_channel_id": "",
    "express_restrictions": "[]",
    "contact": "",
    "phone": "",
    "address": "",
    "status": "active",
    "file": "历史发货成本资料"
  },
  {
    "id": "228303dc-0ad6-4f0e-9aa6-cc42f694f6a4",
    "name": "浙江云战",
    "code": "SUP007",
    "type": "三方",
    "channel": "其他",
    "jd_channel_id": "",
    "express_restrictions": "[]",
    "contact": "",
    "phone": "",
    "address": "",
    "status": "active",
    "file": "历史发货成本资料"
  },
  {
    "id": "3cd88a1d-3739-40f8-af81-22d8b20c6cb7",
    "name": "上海谦半天猫",
    "code": "SUP008",
    "type": "三方",
    "channel": "其他",
    "jd_channel_id": "",
    "express_restrictions": "[]",
    "contact": "",
    "phone": "",
    "address": "",
    "status": "active",
    "file": "历史发货成本资料"
  },
  {
    "id": "d261ff39-39fb-420b-abaa-cad23772d689",
    "name": "上海毅道",
    "code": "SUP009",
    "type": "三方",
    "channel": "其他",
    "jd_channel_id": "",
    "express_restrictions": "[]",
    "contact": "",
    "phone": "",
    "address": "",
    "status": "active",
    "file": "历史发货成本资料"
  },
  {
    "id": "44277ff7-96a9-439a-8eb0-cd473122bb40",
    "name": "深圳碧然晨",
    "code": "SUP010",
    "type": "三方",
    "channel": "其他",
    "jd_channel_id": "",
    "express_restrictions": "[]",
    "contact": "",
    "phone": "",
    "address": "",
    "status": "active",
    "file": "历史发货成本资料"
  },
  {
    "id": "dea83d3d-d793-4fde-a433-a6bdfc7b158a",
    "name": "张家港米盛",
    "code": "SUP011",
    "type": "三方",
    "channel": "其他",
    "jd_channel_id": "",
    "express_restrictions": "[]",
    "contact": "",
    "phone": "",
    "address": "",
    "status": "active",
    "file": "历史发货成本资料"
  },
  {
    "id": "7d99bad5-a3c2-41da-a618-22d4d17baa79",
    "name": "上海至梵",
    "code": "SUP012",
    "type": "三方",
    "channel": "其他",
    "jd_channel_id": "",
    "express_restrictions": "[]",
    "contact": "",
    "phone": "",
    "address": "",
    "status": "active",
    "file": "历史发货成本资料"
  },
  {
    "id": "7b48eacd-8087-4c58-ab55-be754410fccf",
    "name": "杭州舟亢",
    "code": "SUP013",
    "type": "三方",
    "channel": "其他",
    "jd_channel_id": "",
    "express_restrictions": "[]",
    "contact": "",
    "phone": "",
    "address": "",
    "status": "active",
    "file": "历史发货成本资料"
  },
  {
    "id": "a5f3fb5e-3162-4c73-aa13-255fea9bee72",
    "name": "广州威泽",
    "code": "SUP014",
    "type": "三方",
    "channel": "其他",
    "jd_channel_id": "",
    "express_restrictions": "[]",
    "contact": "",
    "phone": "",
    "address": "",
    "status": "active",
    "file": "历史发货成本资料"
  },
  {
    "id": "1ea94bca-bfbe-4e20-9169-7407bf745626",
    "name": "深圳西贝阳光",
    "code": "SUP015",
    "type": "三方",
    "channel": "其他",
    "jd_channel_id": "",
    "express_restrictions": "[]",
    "contact": "",
    "phone": "",
    "address": "",
    "status": "active",
    "file": "历史发货成本资料"
  },
  {
    "id": "ea1483b1-03f5-42e3-b209-939ab6cec979",
    "name": "广东云海",
    "code": "SUP016",
    "type": "三方",
    "channel": "其他",
    "jd_channel_id": "",
    "express_restrictions": "[]",
    "contact": "",
    "phone": "",
    "address": "",
    "status": "active",
    "file": "历史发货成本资料"
  },
  {
    "id": "dac4ab38-8505-4a8a-9bf9-419dfa9e5611",
    "name": "广州超品汇2C主仓",
    "code": "SUP017",
    "type": "三方",
    "channel": "其他",
    "jd_channel_id": "",
    "express_restrictions": "[]",
    "contact": "",
    "phone": "",
    "address": "",
    "status": "active",
    "file": "历史发货成本资料"
  },
  {
    "id": "4b7cd38d-6f31-493c-9ece-d4ea0c863651",
    "name": "天津倾心",
    "code": "SUP018",
    "type": "三方",
    "channel": "其他",
    "jd_channel_id": "",
    "express_restrictions": "[]",
    "contact": "",
    "phone": "",
    "address": "",
    "status": "active",
    "file": "历史发货成本资料"
  },
  {
    "id": "7f2e6cf7-7573-4b70-8bc2-7939b83fe9c0",
    "name": "慈溪腾杰",
    "code": "SUP019",
    "type": "三方",
    "channel": "其他",
    "jd_channel_id": "",
    "express_restrictions": "[]",
    "contact": "",
    "phone": "",
    "address": "",
    "status": "active",
    "file": "历史发货成本资料"
  },
  {
    "id": "753be4d9-d1f0-48fa-976a-c2244f84256d",
    "name": "成都拓普壹",
    "code": "SUP020",
    "type": "三方",
    "channel": "其他",
    "jd_channel_id": "",
    "express_restrictions": "[]",
    "contact": "",
    "phone": "",
    "address": "",
    "status": "active",
    "file": "历史发货成本资料"
  },
  {
    "id": "4f5ac578-16ec-4814-8339-f35ce537ba8b",
    "name": "杭州怡霖",
    "code": "SUP021",
    "type": "三方",
    "channel": "其他",
    "jd_channel_id": "",
    "express_restrictions": "[]",
    "contact": "",
    "phone": "",
    "address": "",
    "status": "active",
    "file": "历史发货成本资料"
  },
  {
    "id": "ae5d67ee-07cd-421d-9a32-9c6821aff2c9",
    "name": "永康珏灵",
    "code": "SUP022",
    "type": "三方",
    "channel": "其他",
    "jd_channel_id": "",
    "express_restrictions": "[]",
    "contact": "",
    "phone": "",
    "address": "",
    "status": "active",
    "file": "历史发货成本资料"
  },
  {
    "id": "898b2ae5-5abc-40a5-913b-d63be6f1712f",
    "name": "中山奔和",
    "code": "SUP023",
    "type": "三方",
    "channel": "其他",
    "jd_channel_id": "",
    "express_restrictions": "[]",
    "contact": "",
    "phone": "",
    "address": "",
    "status": "active",
    "file": "历史发货成本资料"
  },
  {
    "id": "8456905d-b428-4215-a728-d20c2720eaa4",
    "name": "北京兰瑞基",
    "code": "SUP024",
    "type": "三方",
    "channel": "其他",
    "jd_channel_id": "",
    "express_restrictions": "[]",
    "contact": "",
    "phone": "",
    "address": "",
    "status": "active",
    "file": "历史发货成本资料"
  },
  {
    "id": "89027eb1-34d8-49a8-987a-6057bdd212e1",
    "name": "广州齐林",
    "code": "SUP025",
    "type": "三方",
    "channel": "其他",
    "jd_channel_id": "",
    "express_restrictions": "[]",
    "contact": "",
    "phone": "",
    "address": "",
    "status": "active",
    "file": "历史发货成本资料"
  },
  {
    "id": "02b80f18-cc7e-4ff1-b438-0835145dca65",
    "name": "山东怡坤",
    "code": "SUP026",
    "type": "三方",
    "channel": "其他",
    "jd_channel_id": "",
    "express_restrictions": "[]",
    "contact": "",
    "phone": "",
    "address": "",
    "status": "active",
    "file": "历史发货成本资料"
  },
  {
    "id": "fa2468f6-266d-4e14-b0ba-c1b95aa3ecd6",
    "name": "北京国泰昌荣",
    "code": "SUP027",
    "type": "三方",
    "channel": "其他",
    "jd_channel_id": "",
    "express_restrictions": "[]",
    "contact": "",
    "phone": "",
    "address": "",
    "status": "active",
    "file": "历史发货成本资料"
  },
  {
    "id": "f21d16a6-5e5b-4905-a0b5-ee88ed0b2c12",
    "name": "安徽艾森格",
    "code": "SUP028",
    "type": "三方",
    "channel": "其他",
    "jd_channel_id": "",
    "express_restrictions": "[]",
    "contact": "",
    "phone": "",
    "address": "",
    "status": "active",
    "file": "历史发货成本资料"
  },
  {
    "id": "99c3f398-4ae9-403e-80ce-260032162c35",
    "name": "山东新瑞",
    "code": "SUP029",
    "type": "三方",
    "channel": "其他",
    "jd_channel_id": "",
    "express_restrictions": "[]",
    "contact": "",
    "phone": "",
    "address": "",
    "status": "active",
    "file": "历史发货成本资料"
  },
  {
    "id": "a87b5deb-ea94-4bbb-8e51-990c11d44281",
    "name": "上海飞通",
    "code": "SUP030",
    "type": "三方",
    "channel": "其他",
    "jd_channel_id": "",
    "express_restrictions": "[]",
    "contact": "",
    "phone": "",
    "address": "",
    "status": "active",
    "file": "历史发货成本资料"
  },
  {
    "id": "db06e0a1-f03f-42d8-8ba0-3b71e70d5e98",
    "name": "广州金运",
    "code": "SUP031",
    "type": "三方",
    "channel": "其他",
    "jd_channel_id": "",
    "express_restrictions": "[]",
    "contact": "",
    "phone": "",
    "address": "",
    "status": "active",
    "file": "历史发货成本资料"
  },
  {
    "id": "43180a97-3610-4e60-b141-4423b32d0820",
    "name": "佛山多品博美",
    "code": "SUP032",
    "type": "三方",
    "channel": "其他",
    "jd_channel_id": "",
    "express_restrictions": "[]",
    "contact": "",
    "phone": "",
    "address": "",
    "status": "active",
    "file": "历史发货成本资料"
  },
  {
    "id": "f5cd1763-d242-47ed-9654-84b893079a4a",
    "name": "杭州世净",
    "code": "SUP033",
    "type": "三方",
    "channel": "其他",
    "jd_channel_id": "",
    "express_restrictions": "[]",
    "contact": "",
    "phone": "",
    "address": "",
    "status": "active",
    "file": "历史发货成本资料"
  },
  {
    "id": "78cf3f23-1aa6-4b7f-b8e0-331818da29ee",
    "name": "福建翼盛通",
    "code": "SUP034",
    "type": "三方",
    "channel": "其他",
    "jd_channel_id": "",
    "express_restrictions": "[]",
    "contact": "",
    "phone": "",
    "address": "",
    "status": "active",
    "file": "历史发货成本资料"
  },
  {
    "id": "33e4dbff-2e61-41df-94e6-2f2937d5caab",
    "name": "广东金达",
    "code": "SUP035",
    "type": "三方",
    "channel": "其他",
    "jd_channel_id": "",
    "express_restrictions": "[]",
    "contact": "",
    "phone": "",
    "address": "",
    "status": "active",
    "file": "历史发货成本资料"
  },
  {
    "id": "a8ee60ab-4405-45d1-b9e2-e144cc270e44",
    "name": "烟台尚讯",
    "code": "SUP036",
    "type": "三方",
    "channel": "其他",
    "jd_channel_id": "",
    "express_restrictions": "[]",
    "contact": "",
    "phone": "",
    "address": "",
    "status": "active",
    "file": "历史发货成本资料"
  },
  {
    "id": "fd158252-9ac0-4cb0-8ae5-7a388ee6e46c",
    "name": "南京悦途",
    "code": "SUP037",
    "type": "三方",
    "channel": "其他",
    "jd_channel_id": "",
    "express_restrictions": "[]",
    "contact": "",
    "phone": "",
    "address": "",
    "status": "active",
    "file": "历史发货成本资料"
  },
  {
    "id": "65295a5a-5100-4530-a6fe-848c1d73a763",
    "name": "许桂波-昆明浩帆",
    "code": "SUP038",
    "type": "三方",
    "channel": "其他",
    "jd_channel_id": "",
    "express_restrictions": "[]",
    "contact": "",
    "phone": "",
    "address": "",
    "status": "active",
    "file": "历史发货成本资料"
  },
  {
    "id": "e431fc5c-a632-4874-a60d-48e0057706e3",
    "name": "上海海淮",
    "code": "SUP039",
    "type": "三方",
    "channel": "其他",
    "jd_channel_id": "",
    "express_restrictions": "[]",
    "contact": "",
    "phone": "",
    "address": "",
    "status": "active",
    "file": "历史发货成本资料"
  },
  {
    "id": "c84b3ebd-4e59-4323-bc19-1488652f47e7",
    "name": "中山合利和",
    "code": "SUP040",
    "type": "三方",
    "channel": "其他",
    "jd_channel_id": "",
    "express_restrictions": "[]",
    "contact": "",
    "phone": "",
    "address": "",
    "status": "active",
    "file": "历史发货成本资料"
  },
  {
    "id": "fa5f5a84-bd58-40e0-a3bf-12674a6b4308",
    "name": "京东飞通企业账户",
    "code": "SUP041",
    "type": "三方",
    "channel": "其他",
    "jd_channel_id": "",
    "express_restrictions": "[]",
    "contact": "",
    "phone": "",
    "address": "",
    "status": "active",
    "file": "历史发货成本资料"
  },
  {
    "id": "c82d374c-dd96-4260-b468-4142da9a3864",
    "name": "沈阳旺得福",
    "code": "SUP042",
    "type": "三方",
    "channel": "其他",
    "jd_channel_id": "",
    "express_restrictions": "[]",
    "contact": "",
    "phone": "",
    "address": "",
    "status": "active",
    "file": "历史发货成本资料"
  },
  {
    "id": "a5e9b9f9-1136-4e20-a972-9099939f7d5b",
    "name": "广州六里",
    "code": "SUP043",
    "type": "三方",
    "channel": "其他",
    "jd_channel_id": "",
    "express_restrictions": "[]",
    "contact": "",
    "phone": "",
    "address": "",
    "status": "active",
    "file": "历史发货成本资料"
  },
  {
    "id": "d078967b-fc73-4754-a302-fd964bdccfa3",
    "name": "深圳万川",
    "code": "SUP044",
    "type": "三方",
    "channel": "其他",
    "jd_channel_id": "",
    "express_restrictions": "[]",
    "contact": "",
    "phone": "",
    "address": "",
    "status": "active",
    "file": "历史发货成本资料"
  },
  {
    "id": "464d5285-084c-41f6-b4eb-5b04d74d4cfc",
    "name": "杭州艾特未来",
    "code": "SUP045",
    "type": "三方",
    "channel": "其他",
    "jd_channel_id": "",
    "express_restrictions": "[]",
    "contact": "",
    "phone": "",
    "address": "",
    "status": "active",
    "file": "历史发货成本资料"
  },
  {
    "id": "4425e07f-c02e-4b3f-99b3-87cf864bafff",
    "name": "江苏金舜源",
    "code": "SUP046",
    "type": "三方",
    "channel": "其他",
    "jd_channel_id": "",
    "express_restrictions": "[]",
    "contact": "",
    "phone": "",
    "address": "",
    "status": "active",
    "file": "历史发货成本资料"
  },
  {
    "id": "2d25cd99-5e7f-44a9-960f-44fdf7ab4807",
    "name": "中山钜泽",
    "code": "SUP047",
    "type": "三方",
    "channel": "其他",
    "jd_channel_id": "",
    "express_restrictions": "[]",
    "contact": "",
    "phone": "",
    "address": "",
    "status": "active",
    "file": "历史发货成本资料"
  },
  {
    "id": "aa1b8fd9-0b55-4c61-83ab-829331627f06",
    "name": "义乌好吉利",
    "code": "SUP048",
    "type": "三方",
    "channel": "其他",
    "jd_channel_id": "",
    "express_restrictions": "[]",
    "contact": "",
    "phone": "",
    "address": "",
    "status": "active",
    "file": "历史发货成本资料"
  },
  {
    "id": "65ce4326-c2db-47da-8276-4f667c690619",
    "name": "上海礼素",
    "code": "SUP049",
    "type": "三方",
    "channel": "其他",
    "jd_channel_id": "",
    "express_restrictions": "[]",
    "contact": "",
    "phone": "",
    "address": "",
    "status": "active",
    "file": "历史发货成本资料"
  },
  {
    "id": "e544d697-5972-4ff7-af85-861defe68a10",
    "name": "辽宁苏泊尔",
    "code": "SUP050",
    "type": "三方",
    "channel": "其他",
    "jd_channel_id": "",
    "express_restrictions": "[]",
    "contact": "",
    "phone": "",
    "address": "",
    "status": "active",
    "file": "历史发货成本资料"
  },
  {
    "id": "02fb7a3b-5001-4ae1-a6a3-7678d9e5f560",
    "name": "武汉沃克尔",
    "code": "SUP051",
    "type": "三方",
    "channel": "其他",
    "jd_channel_id": "",
    "express_restrictions": "[]",
    "contact": "",
    "phone": "",
    "address": "",
    "status": "active",
    "file": "历史发货成本资料"
  },
  {
    "id": "fde2758d-c819-45fd-89ad-b8b16989dd17",
    "name": "许丽纯-上海飞通京东",
    "code": "SUP052",
    "type": "三方",
    "channel": "其他",
    "jd_channel_id": "",
    "express_restrictions": "[]",
    "contact": "",
    "phone": "",
    "address": "",
    "status": "active",
    "file": "历史发货成本资料"
  },
  {
    "id": "2260a314-b6a0-402d-a126-b7aaf8f8b9ea",
    "name": "深圳红紫金",
    "code": "SUP053",
    "type": "三方",
    "channel": "其他",
    "jd_channel_id": "",
    "express_restrictions": "[]",
    "contact": "",
    "phone": "",
    "address": "",
    "status": "active",
    "file": "历史发货成本资料"
  },
  {
    "id": "01e64a65-7d6e-4ffd-9b42-56adcd35d6f2",
    "name": "上海真礼",
    "code": "SUP054",
    "type": "三方",
    "channel": "其他",
    "jd_channel_id": "",
    "express_restrictions": "[]",
    "contact": "",
    "phone": "",
    "address": "",
    "status": "active",
    "file": "历史发货成本资料"
  },
  {
    "id": "1405a2e1-7cf0-4aa0-b626-41d787624ecc",
    "name": "许桂波-巴南渝跃",
    "code": "SUP055",
    "type": "三方",
    "channel": "其他",
    "jd_channel_id": "",
    "express_restrictions": "[]",
    "contact": "",
    "phone": "",
    "address": "",
    "status": "active",
    "file": "历史发货成本资料"
  },
  {
    "id": "006a43d7-9aec-4c3f-8471-c3235edd0ddf",
    "name": "揭阳汇达",
    "code": "SUP056",
    "type": "三方",
    "channel": "其他",
    "jd_channel_id": "",
    "express_restrictions": "[]",
    "contact": "",
    "phone": "",
    "address": "",
    "status": "active",
    "file": "历史发货成本资料"
  },
  {
    "id": "67efba73-c0a8-4c71-b9fe-a1be8c7d09ba",
    "name": "超品汇-深圳西贝阳光",
    "code": "SUP057",
    "type": "三方",
    "channel": "其他",
    "jd_channel_id": "",
    "express_restrictions": "[]",
    "contact": "",
    "phone": "",
    "address": "",
    "status": "active",
    "file": "历史发货成本资料"
  },
  {
    "id": "1d1dac53-6aef-49e1-84dd-4f8ae3136532",
    "name": "江苏格来德",
    "code": "SUP058",
    "type": "三方",
    "channel": "其他",
    "jd_channel_id": "",
    "express_restrictions": "[]",
    "contact": "",
    "phone": "",
    "address": "",
    "status": "active",
    "file": "历史发货成本资料"
  },
  {
    "id": "9214c341-6ccf-4c8a-b124-2995ea92622e",
    "name": "北京小阳",
    "code": "SUP059",
    "type": "三方",
    "channel": "其他",
    "jd_channel_id": "",
    "express_restrictions": "[]",
    "contact": "",
    "phone": "",
    "address": "",
    "status": "active",
    "file": "历史发货成本资料"
  },
  {
    "id": "0ffb8c3c-5498-4a30-85d3-a2015146dcc6",
    "name": "许桂波-京东飞通企业账户",
    "code": "SUP060",
    "type": "三方",
    "channel": "其他",
    "jd_channel_id": "",
    "express_restrictions": "[]",
    "contact": "",
    "phone": "",
    "address": "",
    "status": "active",
    "file": "历史发货成本资料"
  },
  {
    "id": "a148c2ac-dbb5-4cca-956b-502c2e701d04",
    "name": "上海明心",
    "code": "SUP061",
    "type": "三方",
    "channel": "其他",
    "jd_channel_id": "",
    "express_restrictions": "[]",
    "contact": "",
    "phone": "",
    "address": "",
    "status": "active",
    "file": "历史发货成本资料"
  },
  {
    "id": "bf4c0815-4561-426b-968c-48e388401b1f",
    "name": "深圳苏泊尔一件代发",
    "code": "SUP062",
    "type": "三方",
    "channel": "其他",
    "jd_channel_id": "",
    "express_restrictions": "[]",
    "contact": "",
    "phone": "",
    "address": "",
    "status": "active",
    "file": "历史发货成本资料"
  },
  {
    "id": "4a9cd169-82b5-469d-b9c1-a30ad09948c8",
    "name": "许桂波-京东企业账户",
    "code": "SUP063",
    "type": "三方",
    "channel": "其他",
    "jd_channel_id": "",
    "express_restrictions": "[]",
    "contact": "",
    "phone": "",
    "address": "",
    "status": "active",
    "file": "历史发货成本资料"
  },
  {
    "id": "70838375-2bd0-4b49-8d53-480c57eb5054",
    "name": "上海松蓁",
    "code": "SUP064",
    "type": "三方",
    "channel": "其他",
    "jd_channel_id": "",
    "express_restrictions": "[]",
    "contact": "",
    "phone": "",
    "address": "",
    "status": "active",
    "file": "历史发货成本资料"
  },
  {
    "id": "d74b64a3-bab2-4658-ba90-07fda6a391fd",
    "name": "山东惠宝淘宝",
    "code": "SUP065",
    "type": "三方",
    "channel": "其他",
    "jd_channel_id": "",
    "express_restrictions": "[]",
    "contact": "",
    "phone": "",
    "address": "",
    "status": "active",
    "file": "历史发货成本资料"
  },
  {
    "id": "3a480185-f3ae-495e-a960-e8b4d040bd11",
    "name": "深圳阜昌",
    "code": "SUP066",
    "type": "三方",
    "channel": "其他",
    "jd_channel_id": "",
    "express_restrictions": "[]",
    "contact": "",
    "phone": "",
    "address": "",
    "status": "active",
    "file": "历史发货成本资料"
  },
  {
    "id": "d55e5139-deb9-4d98-a709-b33a690a61af",
    "name": "上海艺冉",
    "code": "SUP067",
    "type": "三方",
    "channel": "其他",
    "jd_channel_id": "",
    "express_restrictions": "[]",
    "contact": "",
    "phone": "",
    "address": "",
    "status": "active",
    "file": "历史发货成本资料"
  },
  {
    "id": "4a895ebd-d6e7-4c10-a60f-a9e3da04a7c8",
    "name": "许桂波-京东",
    "code": "SUP068",
    "type": "三方",
    "channel": "其他",
    "jd_channel_id": "",
    "express_restrictions": "[]",
    "contact": "",
    "phone": "",
    "address": "",
    "status": "active",
    "file": "历史发货成本资料"
  },
  {
    "id": "35ac45cf-0e56-4e76-a55b-068be6f99200",
    "name": "山东新瑞小店",
    "code": "SUP069",
    "type": "三方",
    "channel": "其他",
    "jd_channel_id": "",
    "express_restrictions": "[]",
    "contact": "",
    "phone": "",
    "address": "",
    "status": "active",
    "file": "历史发货成本资料"
  },
  {
    "id": "5ce2576c-7379-4151-b0c0-7b2d131304cb",
    "name": "深圳益庆丰",
    "code": "SUP070",
    "type": "三方",
    "channel": "其他",
    "jd_channel_id": "",
    "express_restrictions": "[]",
    "contact": "",
    "phone": "",
    "address": "",
    "status": "active",
    "file": "历史发货成本资料"
  },
  {
    "id": "3eaa9f30-be43-4d71-93f7-e59dc2fc7f75",
    "name": "河南聚百宏",
    "code": "SUP071",
    "type": "三方",
    "channel": "其他",
    "jd_channel_id": "",
    "express_restrictions": "[]",
    "contact": "",
    "phone": "",
    "address": "",
    "status": "active",
    "file": "历史发货成本资料"
  },
  {
    "id": "6cea1d4b-8249-4a2c-8169-8970a3ee6017",
    "name": "深圳腾辉",
    "code": "SUP072",
    "type": "三方",
    "channel": "其他",
    "jd_channel_id": "",
    "express_restrictions": "[]",
    "contact": "",
    "phone": "",
    "address": "",
    "status": "active",
    "file": "历史发货成本资料"
  },
  {
    "id": "8bb44d72-37ea-4013-90ec-9ebf6251c8b7",
    "name": "宁波中央电暖",
    "code": "SUP073",
    "type": "三方",
    "channel": "其他",
    "jd_channel_id": "",
    "express_restrictions": "[]",
    "contact": "",
    "phone": "",
    "address": "",
    "status": "active",
    "file": "历史发货成本资料"
  },
  {
    "id": "3a3969e7-b1d0-4128-aedf-4f5d2a22b791",
    "name": "杭州九阳豆业",
    "code": "SUP074",
    "type": "三方",
    "channel": "其他",
    "jd_channel_id": "",
    "express_restrictions": "[]",
    "contact": "",
    "phone": "",
    "address": "",
    "status": "active",
    "file": "历史发货成本资料"
  },
  {
    "id": "de3f3410-5a5b-418c-9f91-5023dde478d2",
    "name": "许丽纯-淘宝",
    "code": "SUP075",
    "type": "三方",
    "channel": "其他",
    "jd_channel_id": "",
    "express_restrictions": "[]",
    "contact": "",
    "phone": "",
    "address": "",
    "status": "active",
    "file": "历史发货成本资料"
  },
  {
    "id": "c2fe4dfb-c807-4811-a50c-efaa6d25dca3",
    "name": "广州超品汇2C销退次品仓",
    "code": "SUP076",
    "type": "三方",
    "channel": "其他",
    "jd_channel_id": "",
    "express_restrictions": "[]",
    "contact": "",
    "phone": "",
    "address": "",
    "status": "active",
    "file": "历史发货成本资料"
  },
  {
    "id": "6a662673-a9f6-4e86-be84-671bcf3bcef7",
    "name": "许丽纯-京东",
    "code": "SUP077",
    "type": "三方",
    "channel": "其他",
    "jd_channel_id": "",
    "express_restrictions": "[]",
    "contact": "",
    "phone": "",
    "address": "",
    "status": "active",
    "file": "历史发货成本资料"
  },
  {
    "id": "fb1c3673-8080-41fd-9518-705fb953af3e",
    "name": "许桂波-先锋京东",
    "code": "SUP078",
    "type": "三方",
    "channel": "其他",
    "jd_channel_id": "",
    "express_restrictions": "[]",
    "contact": "",
    "phone": "",
    "address": "",
    "status": "active",
    "file": "历史发货成本资料"
  },
  {
    "id": "108f638f-cd37-4418-afdd-1c911fb8e2dd",
    "name": "上海众繁",
    "code": "SUP079",
    "type": "三方",
    "channel": "其他",
    "jd_channel_id": "",
    "express_restrictions": "[]",
    "contact": "",
    "phone": "",
    "address": "",
    "status": "active",
    "file": "历史发货成本资料"
  },
  {
    "id": "002b1c11-548c-4be3-a71c-9afc9875af86",
    "name": "许桂波-拼多多",
    "code": "SUP080",
    "type": "三方",
    "channel": "其他",
    "jd_channel_id": "",
    "express_restrictions": "[]",
    "contact": "",
    "phone": "",
    "address": "",
    "status": "active",
    "file": "历史发货成本资料"
  }
]